{"cameraMode":{"drawMode":0,"name":"Shaded","section":"Shading Mode"},"sceneLighting":false,"audioPlay":false,"sceneViewState":{"m_AlwaysRefresh":false,"showFog":true,"showSkybox":false,"showFlares":true,"showImageEffects":true,"showParticleSystems":true,"showVisualEffectGraphs":true,"m_FxEnabled":true},"in2DMode":false,"pivot":{"x":677.462158203125,"y":8709.5224609375,"z":-682.0393676757813},"rotation":{"x":0.005477068480104208,"y":0.9906512498855591,"z":-0.1300339698791504,"w":0.04323388636112213},"size":1.1129595041275025,"orthographic":false}